codenotes/__init__.py
codenotes/__main__.py
codenotes/abstract.py
codenotes/exceptions.py
codenotes/cli/__init__.py
codenotes/cli/category.py
codenotes/cli/notes.py
codenotes/cli/tasks.py
codenotes/db/__init__.py
codenotes/db/connection.py
codenotes/db/entities.py
codenotes/db/utilities/__init__.py
codenotes/db/utilities/notes.py
codenotes/db/utilities/notes_categories.py
codenotes/db/utilities/tasks.py
codenotes/db/utilities/tasks_categories.py
codenotes/util/__init__.py
codenotes/util/args.py
codenotes/util/help.py
codenotes/util/sql.py
codenotes/util/text.py
tests/cli/__init__.py
tests/cli/test_category.py
tests/cli/test_notes.py
tests/cli/test_tasks.py
tests/util/__init__.py
tests/util/test_args.py
Codenotes-0.0.2.dist-info/AUTHORS
Codenotes-0.0.2.dist-info/LICENSE
Codenotes-0.0.2.dist-info/METADATA
Codenotes-0.0.2.dist-info/WHEEL
Codenotes-0.0.2.dist-info/entry_points.txt
Codenotes-0.0.2.dist-info/top_level.txt
Codenotes-0.0.2.dist-info/RECORD
