Metadata-Version: 2.1
Name: Codenotes
Version: 0.0.2
Summary: A simple CLI where you can save and view all your created annotations
Home-page: https://github.com/EGAMAGZ/codenotes
Author: Gamaliel Garcia
Author-email: egamagz.dev@outlook.com
License: MIT
Keywords: cli cui tui curses command-line note task codenotes
Platform: UNKNOWN
Classifier: Development Status :: 3 - Alpha
Classifier: Environment :: Console
Classifier: Environment :: Console :: Curses
Classifier: License :: OSI Approved :: MIT License
Classifier: Operating System :: OS Independent
Classifier: Programming Language :: Python :: 3.9
Classifier: Topic :: Office/Business :: Scheduling
Classifier: Typing :: Typed
Requires-Python: >=3.9
Requires-Dist: astroid (==2.4.2)
Requires-Dist: colorama (==0.4.4)
Requires-Dist: commonmark (==0.9.1)
Requires-Dist: isort (==5.6.4)
Requires-Dist: lazy-object-proxy (==1.4.3)
Requires-Dist: mccabe (==0.6.1)
Requires-Dist: py-cui (==0.1.2)
Requires-Dist: Pygments (==2.7.4)
Requires-Dist: pylint (==2.6.0)
Requires-Dist: rich (==9.10.0)
Requires-Dist: six (==1.15.0)
Requires-Dist: toml (==0.10.2)
Requires-Dist: typing-extensions (==3.7.4.3)
Requires-Dist: wcwidth (==0.2.5)
Requires-Dist: windows-curses (==2.2.0)
Requires-Dist: wrapt (==1.12.1)
